junker/__init__.py
junker/__main__.py
junker/compileUI.py
junker/junker.py
junker/ui_junker.py
junker/util.py
junker-0.2.0.dist-info/LICENSE.txt
junker-0.2.0.dist-info/METADATA
junker-0.2.0.dist-info/WHEEL
junker-0.2.0.dist-info/entry_points.txt
junker-0.2.0.dist-info/top_level.txt
junker-0.2.0.dist-info/RECORD
