Metadata-Version: 2.1
Name: junker
Version: 0.2.0
Summary: Junker
Home-page: UNKNOWN
Author: Robert A. McLeod
Author-email: robert.mcleod@unibas.ch
License: BSD
